sciklt/README.md
sciklt/__init__.py
sciklt/aids.py
sciklt/cn.py
sciklt/licence.txt
sciklt/main.py
sciklt/data/AIDS CN NLP/Ubuntu CN Lab.iso
sciklt/data/AIDS CN NLP/AIDS/1. Implement Basic Search Strategies/(A) Breadth First Search.ipynb
sciklt/data/AIDS CN NLP/AIDS/1. Implement Basic Search Strategies/(B) Depth First Search.ipynb
sciklt/data/AIDS CN NLP/AIDS/1. Implement Basic Search Strategies/(C) Uniform Cost Search.ipynb
sciklt/data/AIDS CN NLP/AIDS/1. Implement Basic Search Strategies/(D) Depth Limites Search.ipynb
sciklt/data/AIDS CN NLP/AIDS/1. Implement Basic Search Strategies/(E) Iterative Deepening DFS.ipynb
sciklt/data/AIDS CN NLP/AIDS/10. ANOVA/2_ANOVA.csv
sciklt/data/AIDS CN NLP/AIDS/10. ANOVA/One Way ANOVA (Repeated Measure).ipynb
sciklt/data/AIDS CN NLP/AIDS/10. ANOVA/One Way ANOVA.ipynb
sciklt/data/AIDS CN NLP/AIDS/10. ANOVA/Sample 1 Way ANOVA Test.ipynb
sciklt/data/AIDS CN NLP/AIDS/10. ANOVA/Two Way ANOVA.ipynb
sciklt/data/AIDS CN NLP/AIDS/10. ANOVA/reaction_time.csv
sciklt/data/AIDS CN NLP/AIDS/10. ANOVA/sample_data.csv
sciklt/data/AIDS CN NLP/AIDS/10. ANOVA/sleep_deprivation.csv
sciklt/data/AIDS CN NLP/AIDS/11. Linear Regression/3_Linear.csv
sciklt/data/AIDS CN NLP/AIDS/11. Linear Regression/Linear Regression LAB.ipynb
sciklt/data/AIDS CN NLP/AIDS/11. Linear Regression/Linear Regression New- sklearn.ipynb
sciklt/data/AIDS CN NLP/AIDS/11. Linear Regression/Linear Regression.ipynb
sciklt/data/AIDS CN NLP/AIDS/11. Linear Regression/house_rate.csv
sciklt/data/AIDS CN NLP/AIDS/12. Logistic Regression/Logistic Regression New- sklearn.ipynb
sciklt/data/AIDS CN NLP/AIDS/12. Logistic Regression/Logistic Regression.ipynb
sciklt/data/AIDS CN NLP/AIDS/12. Logistic Regression/default.csv
sciklt/data/AIDS CN NLP/AIDS/12. Logistic Regression/hours_scores_records.csv
sciklt/data/AIDS CN NLP/AIDS/2. Implement A Star And MA Star/(A) Astar.ipynb
sciklt/data/AIDS CN NLP/AIDS/2. Implement A Star And MA Star/(B) IDAstar.ipynb
scikit_learn_1.5.2-1.9.dist-info/METADATA
scikit_learn_1.5.2-1.9.dist-info/WHEEL
scikit_learn_1.5.2-1.9.dist-info/top_level.txt
scikit_learn_1.5.2-1.9.dist-info/RECORD
